{
  "organization": [
    {
      "name": "Conference Chairs",
      "members": [
        {
          "name": "Jarrod Millman",
          "org": "University of California Berkeley, USA"
        },
        {
          "name": "Travis Oliphant",
          "org": "Enthought, Inc., USA"
        }
      ]
    },
    {
      "name": "Program Chairs",
      "members": [
        {
          "name": "Stéfan van der Walt",
          "org": "Applied Mathematics, Stellenbosch University, South Africa"
        },
        {
          "name": "Warren Weckesser",
          "org": "Enthought, Inc., USA"
        }
      ]
    },
    {
      "name": "Program Committee",
      "members": [
        {
          "name": "Francesc Alted",
          "org": "PyTables.org, Spain"
        },
        {
          "name": "Christopher Barker",
          "org": "Oceanographer, NOAA Emergency Response Division, USA"
        },
        {
          "name": "C. Titus Brown",
          "org": "Computer Science and Biology, Michigan State, USA"
        },
        {
          "name": "Robert Cimrman",
          "org": "Mechanics and New Technologies Research, University of West Bohemia, Plzeň, Czech Republic"
        },
        {
          "name": "Darren Dale",
          "org": "Cornell High Energy Synchrotron Source, Cornell University, USA"
        },
        {
          "name": "Fernando Pérez",
          "org": "Neuroscience Institute, UC Berkeley, USA"
        },
        {
          "name": "Prabhu Ramachandran",
          "org": "Aerospace Engineering, IIT Bombay, India"
        },
        {
          "name": "Dharhas Pothin",
          "org": "Texas Water Development Board, Austin, USA"
        },
        {
          "name": "Dan Schult",
          "org": "Department of Mathematics, Colgate University, USA"
        },
        {
          "name": "James Turner",
          "org": "Gemini Observatory, Chile"
        }
      ]
    },
    {
      "name": "Tutorial Chair",
      "members": [
        {
          "name": "Brian Granger",
          "org": "Physics, CalPoly, USA"
        }
      ]
    },
    {
      "name": "Student Sponsorship Chair",
      "members": [
        {
          "name": "Chris Colbert",
          "org": "Enthought, Inc., USA"
        }
      ]
    },
    {
      "name": "Python and Core Technologies Track Chair",
      "members": [
        {
          "name": "Anthony Scopatz",
          "org": "Enthought, Inc., USA"
        }
      ]
    },
    {
      "name": "Python in Data Science Track Chair",
      "members": [
        {
          "name": "Peter Wang",
          "org": "Streamitive, LLC., USA"
        }
      ]
    },
    {
      "name": "Proceedings Reviewers",
      "members": [
        {
          "name": "Jacob VanderPlas",
          "org": "Department of Astronomy, University of Washington",
          "location": ""
        },
        {
          "name": "James Turner",
          "org": "Gemini Observatory",
          "location": "Chile"
        },
        {
          "name": "Yannick Schwartz",
          "org": "",
          "location": "France"
        },
        {
          "name": "Andy R. Terrel",
          "org": "Texas Advanced Computing Center, University of Texas at Austin",
          "location": "USA"
        },
        {
          "name": "Gert-Jan van Rooyen",
          "org": "Telecommunications, Stellenbosch University",
          "location": "South Africa"
        },
        {
          "name": "Tiziano Zito",
          "org": "Bernstein Center for Computational Neuroscience, Humboldt University of Berlin",
          "location": "Berlin, Germany"
        },
        {
          "name": "Mateusz Paprocki",
          "org": "",
          "location": "Wrocław, Poland"
        },
        {
          "name": "Michael Hanke",
          "org": "Center for Behavioral Brain Sciences, University of Magdeburg",
          "location": "Germany"
        },
        {
          "name": "David Warde-Farley",
          "org": "Université de Montréal",
          "location": "Montréal, Canada"
        },
        {
          "name": "Jason Grout",
          "org": "Department of Mathematics and Computer Science, Drake University",
          "location": "Des Moines, IA, USA"
        },
        {
          "name": "Ariel Rokem",
          "org": "Department of Psychology, Stanford University",
          "location": "Palo Alto, CA, USA"
        },
        {
          "name": "Jacob Barhak",
          "org": "??",
          "location": "USA"
        },
        {
          "name": "Travis Vaught",
          "org": "Ben Patterson Management Company, LLC",
          "location": "USA"
        },
        {
          "name": "Nicholas Pinto",
          "org": "MIT",
          "location": "Cambridge, MA, USA"
        },
        {
          "name": "Tony Yu",
          "org": "Brown University",
          "location": "USA"
        }
      ]
    }
  ],
  "series": {
    "xref": {
      "resource_url": "https://conference.scipy.org/proceedings",
      "issn": "2575-9752"
    },
    "doi": "10.25080/issn.2575-9752",
    "title": {
      "full": "Proceedings of the Python in Science Conference"
    }
  },
  "scipy_scholarship": [
    {
      "name": "Chad Baker",
      "org": "University of Texas Austin",
      "location": "Austin, TX"
    },
    {
      "name": "Drew Conway",
      "org": "New York University",
      "location": "New York, NY"
    },
    {
      "name": "Ben Edwards",
      "org": "University of New Mexico",
      "location": "Albuquerque, NM"
    },
    {
      "name": "Christopher Ellison",
      "org": "University of California Davis",
      "location": "Davis, CA"
    },
    {
      "name": "Paul Ivanov",
      "org": "University of California Berkeley",
      "location": "Berkeley, CA"
    },
    {
      "name": "Thinh Lam",
      "org": "University of Texas Austin",
      "location": "Austin, TX"
    },
    {
      "name": "Aaron Meurer",
      "org": "New Mexico Tech",
      "location": "Socorro, NM"
    },
    {
      "name": "Min Ragan-Kelley",
      "org": "University of California Berkeley",
      "location": "Berkeley, CA"
    },
    {
      "name": "Joon Ro",
      "org": "University of Texas Austin",
      "location": "Austin, TX"
    },
    {
      "name": "Skipper Seabold",
      "org": "American University",
      "location": "Washington, D.C."
    },
    {
      "name": "Jordi Torrents",
      "org": "University of Barcelona, IESE Business School",
      "location": "Barcelona, Spain"
    },
    {
      "name": "David Warde-Farley",
      "org": "Université de Montréal",
      "location": "Montréal, Canada"
    }
  ],
  "diversity_scholarship": [
    {
      "name": "",
      "org": ""
    }
  ],
  "proceedings": {
    "copyright": {
      "license": "Creative Commons Attribution License (CCAL)",
      "article": "This is an open-access article distributed under the terms of the Creative Commons Attribution License, which permits unrestricted use, distribution, and reproduction in any medium, provided the original author and source are credited.",
      "proceedings": [
        "The articles in the Proceedings of the Python in Science Conference are copyrighted and owned by their original authors",
        "This is an open-access publication and is distributed under the terms of the Creative Commons Attribution License, which permits unrestricted use, distribution, and reproduction in any medium, provided the original author and source are credited.",
        "For more information, please see:  http://creativecommons.org/licenses/by/3.0/"
      ]
    },
    "xref": {
      "depositor_email": "dniederhut@enthought.com",
      "registrant": "Crossref",
      "depositor_name": "Dillon Niederhut",
      "prefix": "10.25080",
      "resource_url": "https://conference.scipy.org/proceedings"
    },
    "title": {
      "full": "Proceedings of the 10th Python in Science Conference",
      "acronym": "SciPy",
      "ordinal": "10th",
      "short": "PROC. OF THE 10th PYTHON IN SCIENCE CONF. (SCIPY 2011)",
      "conference": "Python in Science Conference"
    },
    "volume": 3,
    "citation_key": "proc-scipy-2011",
    "editor": [
      "Stéfan van der Walt",
      "Jarrod Millman"
    ],
    "isbn": "noisbn",
    "number": 1,
    "doi": "10.25080/Majora-ebaa42b7-014",
    "location": "Austin, Texas",
    "dates": "July 11 - 16",
    "year": "2011",
    "editor_email": []
  }
}
